cpaassdk/__init__.py
cpaassdk/__version__.py
cpaassdk/api.py
cpaassdk/client.py
cpaassdk/config.py
cpaassdk/utils.py
cpaassdk/resources/__init__.py
cpaassdk/resources/conversation.py
cpaassdk/resources/notification.py
cpaassdk/resources/notification_channel.py
cpaassdk/resources/twofactor.py
cpaassdk-1.2.2.dist-info/LICENSE
cpaassdk-1.2.2.dist-info/METADATA
cpaassdk-1.2.2.dist-info/WHEEL
cpaassdk-1.2.2.dist-info/top_level.txt
cpaassdk-1.2.2.dist-info/RECORD
